wdg_lab/__init__.py
wdg_lab/__version__.py
wdg_lab-0.1.1.dist-info/METADATA
wdg_lab-0.1.1.dist-info/WHEEL
wdg_lab-0.1.1.dist-info/entry_points.txt
wdg_lab-0.1.1.dist-info/top_level.txt
wdg_lab-0.1.1.dist-info/RECORD
