Metadata-Version: 2.4
Name: wdg-lab
Version: 0.1.1
Summary: Winding Lab: Your powerful winding design assistant
Author-email: Mingyang Bao <mingyangbob@gmail.com>
Maintainer-email: Mingyang Bao <mingyangbob@gmail.com>
Project-URL: Homepage, https://github.com/DawnEver/wdg-lab
Project-URL: Documentation, https://github.com/DawnEver/wdg-lab
Project-URL: Repository, https://github.com/DawnEver/wdg-lab
Project-URL: Issues, https://github.com/DawnEver/wdg-lab/issues
Requires-Python: >=3.12
Requires-Dist: matplotlib>=3.10.6
Requires-Dist: numpy>=2.2.6
Requires-Dist: pydantic>=2.12.4
Requires-Dist: pint>=0.25.2
Requires-Dist: rtoml>=0.13.0
Requires-Dist: bokeh
Requires-Dist: pyside6-essentials>=6.10.1
Provides-Extra: dev
Requires-Dist: pytest; extra == "dev"
Requires-Dist: pytest-cov; extra == "dev"
Requires-Dist: pytest-mock; extra == "dev"
Requires-Dist: pytest-xdist; extra == "dev"
Requires-Dist: coverage[toml]; extra == "dev"
Requires-Dist: pdoc; extra == "dev"
Requires-Dist: commitizen; extra == "dev"
Requires-Dist: pre-commit; extra == "dev"
Requires-Dist: ruff; extra == "dev"
Provides-Extra: web
Requires-Dist: fastapi; extra == "web"
Requires-Dist: uvicorn; extra == "web"
Requires-Dist: httpx; extra == "web"
